emu_power/__init__.py
emu_power/response_entities.py
emu_power-1.5.dist-info/LICENSE
emu_power-1.5.dist-info/METADATA
emu_power-1.5.dist-info/WHEEL
emu_power-1.5.dist-info/top_level.txt
emu_power-1.5.dist-info/RECORD
