Metadata-Version: 2.1
Name: emu-power
Version: 1.5
Summary: A Python3 API to interface with Rainforest Automation's EMU-2
Home-page: https://github.com/Steve0320/Emu-Api
Author: Steven Bertolucci
Author-email: srbertol@mtu.edu
License: UNKNOWN
Platform: UNKNOWN
Classifier: Programming Language :: Python :: 3
Classifier: License :: OSI Approved :: MIT License
Classifier: Operating System :: OS Independent
Requires-Python: >=3.6
Requires-Dist: pyserial
